locustdb-0.5.6.dist-info/METADATA
locustdb-0.5.6.dist-info/WHEEL
locustdb-0.5.6.dist-info/licenses/LICENSE
locustdb/__init__.py
locustdb/locustdb.cpython-38-aarch64-linux-gnu.so
locustdb-0.5.6.dist-info/RECORD
