Metadata-Version: 2.4
Name: locustdb
Version: 0.5.6
License-File: LICENSE
Summary: Embeddable high-performance analytics database.
Author: Clemens Winter <clemenswinter1@gmail.com>
Author-email: Clemens Winter <clemenswinter1@gmail.com>
Project-URL: Source Code, https://github.com/cswinter/LocustDB
